nulltype/__init__.py
nulltype/__version__.py
jdv_nulltype-1.0.1.dist-info/WHEEL
jdv_nulltype-1.0.1.dist-info/METADATA
jdv_nulltype-1.0.1.dist-info/RECORD
